{
  "name": "see-spot-help",
  "dependencies": {},
  "globalDependencies": {
    "bluebird": "registry:dt/bluebird#2.0.0+20160319051630",
    "cryptojs": "registry:dt/cryptojs#3.1.2+20160317120654",
    "expect": "registry:dt/expect#1.13.4+20160316155526",
    "express": "registry:dt/express#4.0.0+20160317120654",
    "express-serve-static-core": "registry:dt/express-serve-static-core#0.0.0+20160701212727",
    "fbsdk": "registry:dt/fbsdk#0.0.0+20160316155526",
    "firebase": "registry:dt/firebase#2.4.1+20160412125105",
    "fullcalendar": "registry:dt/fullcalendar#1.6.1+20160317120654",
    "jquery": "registry:dt/jquery#1.10.0+20160417213236",
    "jquery.timepicker": "registry:dt/jquery.timepicker#0.3.0+20160316155526",
    "karma": "registry:dt/karma#0.13.9+20160501125529",
    "log4js": "registry:dt/log4js#0.0.0+20160608042355",
    "mime": "registry:dt/mime#0.0.0+20160316155526",
    "mocha": "registry:dt/mocha#2.2.5+20160619032855",
    "moment": "registry:dt/moment#2.8.0+20160316155526",
    "moment-node": "registry:dt/moment-node#2.11.1+20160511043338",
    "moment-timezone": "registry:dt/moment-timezone#0.2.5+20160329220348",
    "node": "registry:dt/node#6.0.0+20160514165920",
    "react": "registry:dt/react#0.14.0+20160423065914",
    "react-addons-test-utils": "registry:dt/react-addons-test-utils#0.14.0+20160427035638",
    "react-bootstrap": "registry:dt/react-bootstrap#0.0.0+20160423135514",
    "require": "registry:dt/require#2.1.20+20160316155526",
    "serve-static": "registry:dt/serve-static#0.0.0+20160606155157"
  }
}
